[
    {
        "targetWord": "Fatal",
        "errorMessage": "FATAL ERROR: System Halted",
        "messageTranslation": "致命的なエラー：システムが停止しました",
        "generalMeaning": "【形】致命的な、命に関わる",
        "generalExample": "A fatal accident (死亡事故)",
        "techMeaning": "プログラムが即死して、もう息をしていない状態",
        "explanation": "再起不能。保存してないデータは諦めよう。",
        "usageContext": "遅刻確定の時",
        "usageExample": "I made a fatal mistake...",
        "usageExampleTranslation": "致命的なミスをしちゃった…",
        "usagePunchline": "Boss: 403 Forbidden",
        "usagePunchlineTranslation": "上司：許さん（アクセス拒否）"
    },
    {
        "targetWord": "Argument",
        "errorMessage": "Invalid Argument",
        "messageTranslation": "無効な引数です",
        "generalMeaning": "【名】口論、議論",
        "generalExample": "They had a heated argument. (彼らは激しく口論した)",
        "techMeaning": "引数（ひきすう）＝ 関数に渡すデータ",
        "explanation": "プログラムに関数を渡すのは、『議論の種』を渡すようなもの。コンピュータと喧嘩してるわけじゃないよ！",
        "usageContext": "夫婦喧嘩の時",
        "usageExample": "Invalid Argument provided.",
        "usageExampleTranslation": "無効な主張（引数）です。",
        "usagePunchline": "Wife: System Shutdown.",
        "usagePunchlineTranslation": "妻：システムシャットダウン（会話終了）"
    },
    {
        "targetWord": "Exception",
        "errorMessage": "Unhandled Exception",
        "messageTranslation": "処理されていない例外が発生しました",
        "generalMeaning": "【名】例外、特例",
        "generalExample": "Everyone liked it, with the exception of Bob.",
        "techMeaning": "想定外のエラー（ルール違反）",
        "explanation": "プログラムにとっての『例外』は『処理できない！』という悲鳴。キャッチしてあげないと落ちるよ。",
        "usageContext": "飲み会で一人だけ飲まない時",
        "usageExample": "I am an Exception.",
        "usageExampleTranslation": "僕は例外（飲まない人）です。",
        "usagePunchline": "Organizer: Error handling required.",
        "usagePunchlineTranslation": "幹事：エラー処理（介抱）が必要だな。"
    },
    {
        "targetWord": "Deprecated",
        "errorMessage": "Deprecated Warning",
        "messageTranslation": "非推奨の警告",
        "generalMeaning": "【動】非難される、反対される",
        "generalExample": "The practice was deprecated.",
        "techMeaning": "非推奨（もう古くさいから使うな）",
        "explanation": "禁止ではないが、『もう時代遅れだから、使うと恥かくよ（そのうち消すよ）』という優しさを含んだ警告。",
        "usageContext": "死語を使った時",
        "usageExample": "Using 'ナウい' is deprecated.",
        "usageExampleTranslation": "「ナウい」の使用は非推奨です。",
        "usagePunchline": "Youth: Warning ignored.",
        "usagePunchlineTranslation": "若者：警告を無視（スルー）"
    },
    {
        "targetWord": "Void",
        "errorMessage": "public void main...",
        "messageTranslation": "戻り値なし（void）のメイン関数",
        "generalMeaning": "【名/形】空っぽ、虚空",
        "generalExample": "Staring into the void. (虚空を見つめる)",
        "techMeaning": "戻り値（返事）がない",
        "explanation": "仕事を頼んでも『虚空』に向かって叫ぶだけ。返事は返ってこない一方通行の命令。",
        "usageContext": "既読スルーされた時",
        "usageExample": "My message returned void.",
        "usageExampleTranslation": "私のメッセージは虚空（無視）を返した。",
        "usagePunchline": "Partner: (No Response)",
        "usagePunchlineTranslation": "相手：（応答なし）"
    },
    {
        "targetWord": "Listen",
        "errorMessage": "EADDRINUSE: address already in use",
        "messageTranslation": "エラー：アドレスは既に使用中です",
        "generalMeaning": "【動】聞く、耳を傾ける",
        "generalExample": "Listen to the music.",
        "techMeaning": "（接続待ちで）耳をすませて待機する",
        "explanation": "サーバーは常にポート（扉）に耳を当てて、アクセスが来るのを『Listen』しているんだ。エラーは『耳が塞がってる』ってこと。",
        "usageContext": "話を聞かない彼氏に",
        "usageExample": "Error: Port 80 not listening.",
        "usageExampleTranslation": "エラー：ポート80（耳）が聞いてません。",
        "usagePunchline": "Girlfriend: Connection Refused.",
        "usagePunchlineTranslation": "彼女：接続拒否（さようなら）。"
    }
]